charm_lensing/__init__.py
charm_lensing/analysis_tools.py
charm_lensing/build_lens_system.py
charm_lensing/config_parser.py
charm_lensing/critical_and_caustic.py
charm_lensing/data_loader.py
charm_lensing/interpolation.py
charm_lensing/likelihood.py
charm_lensing/linear_operators.py
charm_lensing/minimization_parser.py
charm_lensing/mock_data.py
charm_lensing/nifty_connect.py
charm_lensing/plotting.py
charm_lensing/projection_operator.py
charm_lensing/psf_operator.py
charm_lensing/response.py
charm_lensing/space_model.py
charm_lensing/spaces.py
charm_lensing/utils.py
charm_lensing/models/__init__.py
charm_lensing/models/model.py
lenscharm-1.0.0.dist-info/LICENCE
lenscharm-1.0.0.dist-info/METADATA
lenscharm-1.0.0.dist-info/WHEEL
lenscharm-1.0.0.dist-info/top_level.txt
lenscharm-1.0.0.dist-info/RECORD
