Metadata-Version: 2.1
Name: lenscharm
Version: 1.0.0
Summary: A Charming, Bayesian, Strong Lensing Framework
Home-page: https://gitlab.mpcdf.mpg.de/ift/lenscharm
Author: Matteo Guardiani
Author-email: matteo.guardiani@gmail.com
License-File: LICENCE
Requires-Dist: numpy
Requires-Dist: jax
Requires-Dist: jaxlib
Requires-Dist: nifty
Requires-Dist: matplotlib
Requires-Dist: scipy
Requires-Dist: astropy
